common/__init__.py
common/yaml.py
configuration/__init__.py
google_search_origin-1.1.5.dist-info/METADATA
google_search_origin-1.1.5.dist-info/WHEEL
google_search_origin-1.1.5.dist-info/top_level.txt
google_search_origin-1.1.5.dist-info/RECORD
